{
    "DataType": "ProceduralGridItemData",
    "DataVersion": 0,
    "GameVersion": "0.3.4f4",
    "GUID": "3ef0946b-3c1e-42fa-a23d-7ffd13977142",
    "ItemString": "{\n    \"DataType\": \"ItemData\",\n    \"DataVersion\": 0,\n    \"GameVersion\": \"0.3.4f4\",\n    \"ID\": \"ledgrowlight\",\n    \"Quantity\": 1\n}",
    "LoadOrder": 50,
    "Rotation": 0,
    "FootprintMatches": [
        {
            "TileOwnerGUID": "39ae61b8-08e9-4008-9aa9-5eef442e462c",
            "TileIndex": 2,
            "FootprintCoordinate": {
                "x": 0.0,
                "y": 0.0
            }
        },
        {
            "TileOwnerGUID": "39ae61b8-08e9-4008-9aa9-5eef442e462c",
            "TileIndex": 1,
            "FootprintCoordinate": {
                "x": 0.0,
                "y": 1.0
            }
        },
        {
            "TileOwnerGUID": "39ae61b8-08e9-4008-9aa9-5eef442e462c",
            "TileIndex": 3,
            "FootprintCoordinate": {
                "x": 1.0,
                "y": 0.0
            }
        },
        {
            "TileOwnerGUID": "39ae61b8-08e9-4008-9aa9-5eef442e462c",
            "TileIndex": 0,
            "FootprintCoordinate": {
                "x": 1.0,
                "y": 1.0
            }
        }
    ]
}